cateyes/__init__.py
cateyes/classification.py
cateyes/setup.py
cateyes/utils.py
cateyes/visualization.py
cateyes-0.0.5.dist-info/METADATA
cateyes-0.0.5.dist-info/WHEEL
cateyes-0.0.5.dist-info/dependency_links.txt
cateyes-0.0.5.dist-info/top_level.txt
cateyes-0.0.5.dist-info/RECORD
