Metadata-Version: 2.1
Name: cateyes
Version: 0.0.5
Summary: Uniform Categorization of Eyetracking in Python.
Home-page: https://github.com/DiGyt/cateyes
Author: Dirk Gütlin
Author-email: dirk.guetlin@gmail.com
License: BSD-3
Keywords: Eyetracking classification
Classifier: Development Status :: 3 - Alpha
Classifier: Topic :: Utilities
Classifier: License :: OSI Approved :: BSD License
Requires-Dist: numpy
Requires-Dist: scipy
Requires-Dist: matplotlib
Requires-Dist: remodnav
